<?xml version='1.0' encoding='UTF-8'?>
<?xml-stylesheet media="screen"              title="Dictionary view"   href="../../giella-core/dicts/scripts/gt_dictionary_XXE.css"     type="text/css"?>
<?xml-stylesheet media="screen"              title="Hierarchical view" href="../../giella-core/dicts/scripts/gt_dictionary_XXE_alt.css" type="text/css" alternate="yes" ?>
<?xml-stylesheet media="print,tv,projection" title="Dictionary view"   href="../../giella-core/dicts/scripts/gt_dictionary.css"         type="text/css"?>
<?xml-stylesheet media="print,tv,projection" title="Hierarchical view" href="../../giella-core/dicts/scripts/gt_dictionary_alt.css"     type="text/css" alternate="yes" ?>
<!DOCTYPE r PUBLIC "-//DivvunGiellatekno//DTD Dictionaries//Multilingual" "../scripts/dict_fkvnob.dtd">
<r id="fkvnob" xml:lang="fkv">
   <lics>
      <lic xml:lang="en">
This code is made available under a Creative Commons Attribution license
<a>http://creativecommons.org/licenses/by/3.0/no/deed.en</a>.

You are free to copy, distribute and adapt the work, as long as you always give
proper attribution using the attribution text below.

For the full license text, see the link above.</lic>
      <ref>Work by Terje Aronsen and Verena Schall at Kainun institutti, Giellatekno at UiT, Divvun at the Norwegian Saami Parliament,
          and members of the language communities. Source code
          available at <a>https://victorio.uit.no/langtech/trunk/</a>.</ref>
      <sourcenote>
     THIS TEXT IS THE ORIGINAL SOURCE CODE. This is NOT a fully styled and
     published dictionary. As such it can and
     will contain unfinished entries, unpublished entries, entries with
     objectionable translations, etc. If you find any errors or want to add more
     words, download the file, edit it, and send it back to
     <a>mailto:divvun@samediggi.no</a> and <a>mailto:giellatekno@hum.uit.no</a>.
     Please also note that the entries are not necessarily sorted,
     or could be wrongly sorted.
     </sourcenote>
   </lics>
   <e src="ki">
      <lg>
         <l pos="Interj">paljon onnee päiväle</l>
      </lg>
      <mg>
         <tg xml:lang="nob">
            <t pos="Interj">gratulerer med dagen</t>
            <xg>
            <x>Paljon onnee sinuleki!</x>
            <xt>Gratulerer til deg også!</xt>
            </xg>
         </tg>
      </mg>
   </e>
      <e src="ki">
      <lg>
         <l pos="Interj">onnee</l>
      </lg>
      <mg>
         <tg xml:lang="nob">
            <t pos="Interj">gratulerer</t>
         </tg>
      </mg>
   </e>
      <e src="ki">
      <lg>
         <l pos="Interj">hyvvää mukkaa</l>
      </lg>
      <mg>
         <tg xml:lang="nob">
            <t pos="Interj">god tur</t>
         </tg>
      </mg>
   </e>
      <e src="ki">
      <lg>
         <l pos="Interj">huom.</l>
      </lg>
      <mg>
         <tg xml:lang="nob">
            <t pos="Interj">obs</t>
         </tg>
      </mg>
   </e>
   <e src="mj">
      <lg>
         <l pos="Interj">riivattu</l>
      </lg>
      <mg>
         <tg xml:lang="nob">
            <t pos="Interj">pokker</t>
            <xg>
               <x>Voi riivattu!</x>
               <xt>Det var som pokker!</xt>
            </xg>
         </tg>
      </mg>
   </e>
   <e src="mj">
      <lg>
         <l pos="Interj">poka</l>
      </lg>
      <mg>
         <tg xml:lang="nob">
            <t pos="Interj">jammen</t>
            <xg>
               <x>Joo poka se oli reisu!</x>
               <xt>Det var jammen noe til reise!</xt>
            </xg>
         </tg>
      </mg>
   </e>
   <e src="mj">
      <lg>
         <l pos="Interj">pahus</l>
      </lg>
      <mg>
         <tg xml:lang="nob">
            <t pos="Interj">søren</t>
         </tg>
      </mg>
   </e>
   <e src="ai">
      <lg>
         <l pos="Interj">aamen</l>
      </lg>
      <mg>
         <tg xml:lang="nob">
            <t pos="Interj">amen</t>
         </tg>
      </mg>
   </e>
   <e src="ai">
      <lg>
         <l pos="Interj">ai</l>
      </lg>
      <mg>
         <tg xml:lang="nob">
            <t pos="Interj">å</t>
            <t pos="Interj">au</t>
         </tg>
      </mg>
   </e>
   <e src="ta;ai">
      <lg>
         <l pos="Interj">antheeksi</l>
      </lg>
      <mg>
         <tg xml:lang="nob">
            <t pos="Interj">unnskyld</t>
            <t pos="Interj">om forlatelse</t>
         </tg>
      </mg>
   </e>
   <e src="ai">
      <lg>
         <l pos="Interj">hups</l>
      </lg>
      <mg>
         <tg xml:lang="nob">
            <t pos="Interj">vips</t>
         </tg>
      </mg>
   </e>
   <e src="ta;ai">
      <lg>
         <l pos="Interj">hyvästi</l>
      </lg>
      <mg>
         <tg xml:lang="nob">
            <t pos="Interj">adjø</t>
            <t pos="Interj">farvel</t>
         </tg>
      </mg>
   </e>
   <e src="ai">
      <lg>
         <l pos="Interj">häh</l>
      </lg>
      <mg>
         <tg xml:lang="nob">
            <t pos="Interj">hæ</t>
         </tg>
      </mg>
   </e>
   <e src="es">
      <lg>
         <l pos="Interj">täh</l>
      </lg>
      <mg>
         <tg xml:lang="nob">
            <t pos="Interj">hæ</t>
         </tg>
      </mg>
   </e>
   <e src="es">
      <lg>
         <l pos="Interj">na</l>
      </lg>
      <mg>
         <tg xml:lang="nob">
            <t pos="Interj">nja</t>
         </tg>
      </mg>
   </e>
   <e src="ai">
      <lg>
         <l pos="Interj">jaa</l>
      </lg>
      <mg>
         <tg xml:lang="nob">
            <t pos="Interj">ja vel</t>
         </tg>
      </mg>
   </e>
   <e src="ai">
      <lg>
         <l pos="Interj">jaha</l>
      </lg>
      <mg>
         <tg xml:lang="nob">
            <t pos="Interj">jaha</t>
         </tg>
      </mg>
   </e>
   <e src="ta;ai">
      <lg>
         <l pos="Interj">joo</l>
      </lg>
      <mg>
         <tg xml:lang="nob">
            <t pos="Interj">jo</t>
            <t pos="Interj">ja</t>
         </tg>
      </mg>
   </e>
   <e src="ta;ai">
      <lg>
         <l pos="Interj">kyllä</l>
      </lg>
      <mg>
         <tg xml:lang="nob">
            <t pos="Interj">jo</t>
            <t pos="Interj">ja</t>
         </tg>
      </mg>
   </e>
   <e src="ai">
      <lg>
         <l pos="Interj">liki-</l>
      </lg>
      <mg>
         <tg xml:lang="nob">
            <t pos="Interj">nær-</t>
         </tg>
      </mg>
   </e>
   <e src="ai">
      <lg>
         <l pos="Interj">moro</l>
      </lg>
      <mg>
         <tg xml:lang="nob">
            <t pos="Interj">god morgen</t>
         </tg>
      </mg>
   </e>
   <e src="uit">
      <lg>
         <l pos="Interj">hei</l>
      </lg>
      <mg>
         <tg xml:lang="nob">
            <t pos="Interj">hei</t>
         </tg>
      </mg>
   </e>
   <e src="uit">
      <lg>
         <l pos="Interj">halloo</l>
      </lg>
      <mg>
         <tg xml:lang="nob">
            <t pos="Interj">hallo</t>
         </tg>
      </mg>
   </e>
   <e src="ta">
      <lg>
         <l pos="Interj">noh</l>
      </lg>
      <mg>
         <tg xml:lang="nob">
            <t pos="Interj">nå</t>
         </tg>
      </mg>
   </e>
   <e src="ai">
      <lg>
         <l pos="Interj">näkemhiin</l>
      </lg>
      <mg>
         <tg xml:lang="nob">
            <t pos="Interj">på gjensyn</t>
         </tg>
      </mg>
   </e>
   <e src="ta">
      <lg>
         <l pos="Interj">näkemiin</l>
      </lg>
      <mg>
         <tg xml:lang="nob">
            <t pos="Interj">på gjensyn</t>
         </tg>
      </mg>
   </e>
   <e src="ai">
      <lg>
         <l pos="Interj">ohhoh</l>
      </lg>
      <mg>
         <tg xml:lang="nob">
            <t pos="Interj">åhå</t>
         </tg>
      </mg>
   </e>
   <e src="ai">
      <lg>
         <l pos="Interj">oo</l>
      </lg>
      <mg>
         <tg xml:lang="nob">
            <t pos="Interj">å ja</t>
         </tg>
      </mg>
   </e>
   <e src="ta">
      <lg>
         <l pos="Interj">perhana</l>
      </lg>
      <mg>
         <tg xml:lang="nob">
            <t pos="Interj">svarte</t>
         </tg>
      </mg>
   </e>
   <e src="ta">
      <lg>
         <l pos="Interj">päivää</l>
      </lg>
      <mg>
         <tg xml:lang="nob">
            <t pos="Interj">god dag</t>
            <xg>
               <x>Hyvvää päivää!</x>
               <xt>God dag!</xt>
            </xg>
         </tg>
      </mg>
   </e>
   <e src="ki">
      <lg>
         <l pos="Interj">aamuu</l>
      </lg>
      <mg>
         <tg xml:lang="nob">
            <t pos="Interj">god morgen</t>
            <xg>
               <x>Hyvvää aamuu!</x>
               <xt>God morgen!</xt>
            </xg>
         </tg>
      </mg>
   </e>
   <e src="ki">
      <lg>
         <l pos="Interj">hyvvää yötä</l>
      </lg>
      <mg>
         <tg xml:lang="nob">
            <t pos="Interj">god natt</t>
         </tg>
      </mg>
   </e>
   <e src="ki">
      <lg>
         <l pos="Interj">hyvvää vyötä</l>
      </lg>
      <mg>
         <tg xml:lang="nob">
            <t pos="Interj">god natt</t>
         </tg>
      </mg>
   </e>
   <e src="ki">
      <lg>
         <l pos="Interj">hyvvää ilttaa</l>
      </lg>
      <mg>
         <tg xml:lang="nob">
            <t pos="Interj">god kveld</t>
         </tg>
      </mg>
   </e>
   <e src="uit">
      <lg>
         <l pos="Interj">terve</l>
      </lg>
      <mg>
         <tg xml:lang="nob">
            <t pos="Interj">hei</t>
         </tg>
      </mg>
   </e>
   <e src="ta">
      <lg>
         <l pos="Interj">saakeli</l>
      </lg>
      <mg>
         <tg xml:lang="nob">
            <t pos="Interj">svarte</t>
         </tg>
      </mg>
   </e>
   <e src="ai">
      <lg>
         <l pos="Interj">tervettulemaa</l>
      </lg>
      <mg>
         <tg xml:lang="nob">
            <t pos="Interj">velkommen</t>
         </tg>
      </mg>
   </e>
   <e src="ai">
      <lg>
         <l pos="Interj">voi</l>
      </lg>
      <mg>
         <tg xml:lang="nob">
            <t pos="Interj">oi</t>
         </tg>
      </mg>
   </e>
   <e src="ta">
      <lg>
         <l pos="Interj">voi-voi</l>
      </lg>
      <mg>
         <tg xml:lang="nob">
            <t pos="Interj">oi-oi</t>
         </tg>
      </mg>
   </e>
   <e src="es">
      <lg>
         <l pos="Interj">helskatti</l>
      </lg>
      <mg>
         <tg xml:lang="nob">
            <t pos="Interj">helsike</t>
         </tg>
      </mg>
   </e>
   <e src="es">
      <lg>
         <l pos="Interj">voi tomppeli senthään</l>
      </lg>
      <mg>
         <tg xml:lang="nob">
            <t pos="Interj">åh, søren heller</t>
         </tg>
      </mg>
   </e>
   <e src="es">
      <lg>
         <l pos="Interj">voi tomppeliitten tomppeli</l>
      </lg>
      <mg>
         <tg xml:lang="nob">
            <t pos="Interj">åh, dobbeltsøren</t>
         </tg>
      </mg>
   </e>
   <e src="es">
      <lg>
         <l pos="Interj">hys</l>
      </lg>
      <mg>
         <tg xml:lang="nob">
            <t pos="Interj">hysj</t>
         </tg>
      </mg>
   </e>
   <e src="es">
      <lg>
         <l pos="Interj">moora</l>
      </lg>
      <mg>
         <tg xml:lang="nob">
            <t pos="Interj">god morgen</t>
         </tg>
      </mg>
   </e>
   <e src="es">
      <lg>
         <l pos="Interj">kiitos osasta</l>
      </lg>
      <mg>
         <tg xml:lang="nob">
            <t pos="Interj">takk for laget</t>
         </tg>
      </mg>
   </e>
   <e src="es">
      <lg>
         <l pos="Interj">Herra siunakhoon</l>
      </lg>
      <mg>
         <tg xml:lang="nob">
            <t pos="Interj">jøss</t>
         </tg>
      </mg>
   </e>
   <e src="es">
      <lg>
         <l pos="Interj">Herra varjelkhoon</l>
      </lg>
      <mg>
         <tg xml:lang="nob">
            <t pos="Interj">Gud forby</t>
         </tg>
      </mg>
   </e>
   <e src="es">
      <lg>
         <l pos="Interj">voi veikkoinen</l>
      </lg>
      <mg>
         <tg xml:lang="nob">
            <t pos="Interj">oi stakkars</t>
         </tg>
      </mg>
   </e>
   <e src="ki">
      <lg>
         <l pos="Interj">voi vittu</l>
      </lg>
      <mg>
         <tg xml:lang="nob">
            <t pos="Interj">fy fitte</t>
            <t pos="Interj">fy faen</t>
         </tg>
      </mg>
   </e>
   <e src="ki">
      <lg>
         <l pos="Interj">voi sakuri</l>
      </lg>
      <mg>
         <tg xml:lang="nob">
            <t pos="Interj">fy Sakarias</t>
         </tg>
      </mg>
   </e>
   <e src="ki">
      <lg>
         <l pos="Interj">herra jumala</l>
      </lg>
      <mg>
         <tg xml:lang="nob">
            <t pos="Interj">herregud</t>
         </tg>
      </mg>
   </e>
   <e src="ki">
      <lg>
         <l pos="Interj">voi hyvänen aika</l>
      </lg>
      <mg>
         <tg xml:lang="nob">
            <t pos="Interj">du store min tid</t>
         </tg>
      </mg>
   </e>
   <e src="ki">
      <lg>
         <l pos="Interj">hyvvää viikkoo</l>
      </lg>
      <mg>
         <tg xml:lang="nob">
            <t pos="Interj">ha en fin uke</t>
         </tg>
      </mg>
   </e>
</r>
